cubicweb_sentry/__init__.py
cubicweb_sentry/__pkginfo__.py
cubicweb_sentry/entities.py
cubicweb_sentry/site_cubicweb.py
cubicweb_sentry-1.1.0.dist-info/METADATA
cubicweb_sentry-1.1.0.dist-info/WHEEL
cubicweb_sentry-1.1.0.dist-info/entry_points.txt
cubicweb_sentry-1.1.0.dist-info/top_level.txt
cubicweb_sentry-1.1.0.dist-info/RECORD
